LICENSE.md
MANIFEST.in
README
README.md
setup.py
tclocalizable/__init__.py
tclocalizable/localized_string.py
tclocalizable/strings_table.py
tclocalizable.egg-info/PKG-INFO
tclocalizable.egg-info/SOURCES.txt
tclocalizable.egg-info/dependency_links.txt
tclocalizable.egg-info/top_level.txt