Metadata-Version: 1.1
Name: tclocalizable
Version: 0.0.7
Summary: Localizable utilities of Cocoa (OS X and iOS)
Home-page: https://github.com/tickleapp/tclocalizable
Author: sodas
Author-email: sodas@tickleapp.com
License: Apache License 2.0
Platform: UNKNOWN
Classifier: Development Status :: 3 - Alpha
Classifier: Environment :: Console
Classifier: Intended Audience :: Developers
Classifier: License :: OSI Approved :: Apache Software License
Classifier: Operating System :: MacOS :: MacOS X
Classifier: Operating System :: POSIX :: Linux
Classifier: Operating System :: Unix
Classifier: Programming Language :: Python :: 3.4
Classifier: Topic :: Software Development
Classifier: Topic :: Utilities
